{
  "id": "182/a",
  "name": "Personenauto in sloot",
  "place": "Sloot",
  "place_array": ["Sloot"],
  "average_credits": 2290,
  "generated_by": "",
  "icons": [
    "/images/caraccident_gruen.png",
    "/images/caraccident_gelb.png",
    "/images/caraccident_rot.png"
  ],
  "requirements": {
    "battalion_chief_vehicles": 1,
    "diver_units": 1,
    "heavy_rescue_vehicles": 1,
    "firetrucks": 1,
    "police_cars": 2
  },
  "chances": {
    "diver_units": 80,
    "heavy_rescue_vehicles": 40,
    "patient_transport": 90
  },
  "additional": {
    "possible_patient": 2,
    "filter_id": "firehouse_missions",
    "possible_crashed_car_max": 1,
    "patient_specialization_ids": [4],
    "patient_specialization_captions": ["Traumatologie"],
    "patient_specializations": "Traumatologie"
  },
  "prerequisites": {
    "main_building": 0,
    "wasserrettung": 1,
    "rescue_stations": 2,
    "police_stations": 2,
    "tow_trucks": 1,
    "fire_stations": 6
  },
  "overlay_index": null,
  "base_mission_id": 182,
  "additive_overlays": "a",
  "mission_categories": ["fire"]
}
