{
  "id": "597",
  "name": "Brand in asielzoekerscentrum",
  "place": "Asielzoekerscentrum",
  "place_array": [
    "Asielzoekerscentrum"
  ],
  "average_credits": 170,
  "generated_by": "",
  "icons": [
    "/images/fire_gruen.png",
    "/images/fire_gelb.png",
    "/images/fire_rot.png"
  ],
  "requirements": {
    "firetrucks": 1
  },
  "chances": {},
  "additional": {
    "expansion_missions_ids": [
      598
    ],
    "filter_id": "firehouse_missions",
    "fire_alarm_system_possible": true
  },
  "prerequisites": {
    "main_building": 0,
    "fire_stations": 1
  },
  "overlay_index": null,
  "base_mission_id": 597,
  "additive_overlays": "",
  "mission_categories": [
    "fire",
    "urban"
  ]
}
