{
  "id": "941",
  "name": "Persoon opgesloten in voertuig",
  "place": "",
  "place_array": [],
  "average_credits": 500,
  "generated_by": "",
  "icons": [
    "/images/bus_gruen.png",
    "/images/bus_gelb.png",
    "/images/bus_rot.png"
  ],
  "requirements": {
    "police_cars": 1
  },
  "chances": {},
  "additional": {
    "filter_id": "police_station_missions"
  },
  "prerequisites": {
    "main_building": 5,
    "police_stations": 1
  },
  "overlay_index": null,
  "base_mission_id": 941,
  "additive_overlays": "",
  "mission_categories": [
    "police"
  ]
}
