{
  "id": "1221",
  "name": "Ongeval met elektrische step",
  "place": "",
  "place_array": [],
  "average_credits": 500,
  "generated_by": "",
  "icons": [
    "/images/ambulance_gruen.png",
    "/images/ambulance_gelb.png",
    "/images/ambulance_rot.png"
  ],
  "requirements": {
    "police_cars": 1
  },
  "chances": {
    "nef": 60,
    "patient_transport": 90
  },
  "additional": {
    "possible_patient": 1,
    "possible_patient_min": 1,
    "filter_id": "ambulance_station_missions",
    "patient_specialization_ids": [4],
    "patient_specialization_captions": ["Traumatologie"],
    "patient_specializations": "Traumatologie"
  },
  "prerequisites": {
    "main_building": 3,
    "rescue_stations": 10,
    "police_stations": 1
  },
  "overlay_index": null,
  "base_mission_id": 1221,
  "additive_overlays": "",
  "mission_categories": ["ambulance"]
}
