{
  "id": "1052-0",
  "name": "Brand overheidsgebouw",
  "place": "",
  "place_array": [],
  "average_credits": 1690,
  "generated_by": "",
  "icons": [
    "/images/fire_gruen.png",
    "/images/fire_gelb.png",
    "/images/fire_rot.png"
  ],
  "requirements": {
    "platform_trucks": 1,
    "battalion_chief_vehicles": 1,
    "firetrucks": 2,
    "police_cars": 2
  },
  "chances": {
    "patient_transport": 100
  },
  "additional": {
    "possible_patient": 2,
    "filter_id": "firehouse_missions",
    "fire_alarm_system_possible": true,
    "patient_specialization_ids": [
      4
    ],
    "patient_specialization_captions": [
      "Traumatologie"
    ],
    "patient_specializations": "Traumatologie"
  },
  "prerequisites": {
    "main_building": 0,
    "rescue_stations": 2,
    "police_stations": 2,
    "fire_stations": 6
  },
  "overlay_index": 0,
  "base_mission_id": 1052,
  "additive_overlays": "",
  "mission_categories": [
    "fire",
    "urban"
  ]
}
