{
  "id": "458-0",
  "name": "Brand in manege",
  "place": "Manege",
  "place_array": [
    "Manege"
  ],
  "average_credits": 3830,
  "generated_by": "",
  "icons": [
    "/images/fire_gruen.png",
    "/images/fire_gelb.png",
    "/images/fire_rot.png"
  ],
  "requirements": {
    "platform_trucks": 1,
    "battalion_chief_vehicles": 1,
    "mobile_command_vehicles": 1,
    "foam": 1,
    "water_tankers": 1,
    "foam_needed": 250,
    "firetrucks": 3
  },
  "chances": {
    "mobile_command_vehicles": 50
  },
  "additional": {
    "filter_id": "firehouse_missions"
  },
  "prerequisites": {
    "main_building": 0,
    "fire_support_count": 1,
    "fire_stations": 13
  },
  "overlay_index": 0,
  "base_mission_id": 458,
  "additive_overlays": "",
  "mission_categories": [
    "fire",
    "urban",
    "fire_support_specialization"
  ]
}
