{
  "id": "611",
  "name": "Brand in nachtclub",
  "place": "Café/Club",
  "place_array": [
    "Café/Club"
  ],
  "average_credits": 3350,
  "generated_by": "",
  "icons": [
    "/images/fire_gruen.png",
    "/images/fire_gelb.png",
    "/images/fire_rot.png"
  ],
  "requirements": {
    "platform_trucks": 1,
    "battalion_chief_vehicles": 1,
    "ovdp": 1,
    "firetrucks": 2,
    "police_cars": 4
  },
  "chances": {
    "platform_trucks": 65,
    "patient_transport": 100
  },
  "additional": {
    "possible_patient": 4,
    "possible_patient_min": 1,
    "expansion_missions_ids": [
      612
    ],
    "max_possible_prisoners": 2,
    "filter_id": "firehouse_missions",
    "patient_specialization_ids": [
      4
    ],
    "patient_specialization_captions": [
      "Traumatologie"
    ],
    "patient_specializations": "Traumatologie"
  },
  "prerequisites": {
    "main_building": 0,
    "rescue_stations": 3,
    "police_stations": 5,
    "fire_stations": 6
  },
  "overlay_index": null,
  "base_mission_id": 611,
  "additive_overlays": "",
  "mission_categories": [
    "fire",
    "urban"
  ]
}
